README.md
setup.py
squinky/__init__.py
squinky/classifier.py
squinky/constants.py
squinky/helpers.py
squinky/sentence.py
squinky/word.py
squinky.egg-info/PKG-INFO
squinky.egg-info/SOURCES.txt
squinky.egg-info/dependency_links.txt
squinky.egg-info/requires.txt
squinky.egg-info/top_level.txt
squinky/data/__init__.py
squinky/data/download.py
squinky/lib/__init__.py
squinky/lib/nlp/__init__.py
squinky/lib/nlp/chunktagger.py
squinky/lib/nlp/lemmatizer.py
squinky/lib/nlp/postagger.py
squinky/lib/nlp/stemmer.py
squinky/lib/nlp/verbs.txt
squinky/models/form_classifier.p
squinky/models/impl_classifier.p
squinky/models/info_classifier.p
squinky/vectorizers/form_vectorizer.p
squinky/vectorizers/impl_vectorizer.p
squinky/vectorizers/info_vectorizer.p