Metadata-Version: 1.1
Name: squinky
Version: 0.1.0
Summary: Classifiers for formality, informativeness, and implicature trained on the SQUINKY! corpus.
Home-page: https://github.com/meyersbs/squinky
Author: Benjamin S. Meyers
Author-email: bsm9339@rit.edu
License: The MIT License (MIT) Copyright (c) 2017 Benjamin S. Meyers
Keywords: nlp,natural language,natural language processing,formality,informativeness,implicature,squinky
Platform: UNKNOWN
Classifier: Development Status :: 4 - Beta
Classifier: Intended Audience :: Science/Research
Classifier: License :: OSI Approved :: MIT License
Classifier: Natural Language :: English
Classifier: Programming Language :: Python :: 3
Classifier: Programming Language :: Python :: 3.4
Classifier: Programming Language :: Python :: 3.5
Classifier: Programming Language :: Python :: 3.6
Classifier: Topic :: Scientific/Engineering :: Information Analysis
Classifier: Topic :: Software Development :: Libraries :: Python Modules
Classifier: Topic :: Text Processing :: Linguistic
